sfrbox_api/__init__.py
sfrbox_api/bridge.py
sfrbox_api/cli/__init__.py
sfrbox_api/cli/__main__.py
sfrbox_api/exceptions.py
sfrbox_api/helpers.py
sfrbox_api/models.py
sfrbox_api/py.typed
sfrbox_api-0.0.15.dist-info/METADATA
sfrbox_api-0.0.15.dist-info/WHEEL
sfrbox_api-0.0.15.dist-info/entry_points.txt
sfrbox_api-0.0.15.dist-info/licenses/LICENSE
sfrbox_api-0.0.15.dist-info/RECORD
