Metadata-Version: 2.4
Name: sfrbox-api
Version: 0.0.15
Summary: SFR Box API
License: MIT
License-File: LICENSE
Keywords: sfrbox,router
Author: epenet
Requires-Python: >=3.9.2,<4.0
Classifier: Intended Audience :: Developers
Classifier: Intended Audience :: System Administrators
Classifier: License :: OSI Approved :: MIT License
Classifier: Operating System :: OS Independent
Classifier: Programming Language :: Python :: 3
Classifier: Programming Language :: Python :: 3.10
Classifier: Programming Language :: Python :: 3.11
Classifier: Programming Language :: Python :: 3.12
Classifier: Programming Language :: Python :: 3.13
Classifier: Programming Language :: Python :: 3.14
Classifier: Programming Language :: Python :: 3.9
Classifier: Topic :: Home Automation
Provides-Extra: cli
Requires-Dist: anyio (>=4.4.0)
Requires-Dist: click (>=8.0.1) ; extra == "cli"
Requires-Dist: defusedxml (>=0.7.1)
Requires-Dist: httpx (>=0.23.1)
Requires-Dist: mashumaro (>=3.13.1)
Project-URL: Changelog, https://github.com/hacf-fr/sfrbox-api/releases
Project-URL: Documentation, https://sfrbox-api.readthedocs.io
Project-URL: Homepage, https://github.com/hacf-fr/sfrbox-api
Project-URL: Repository, https://github.com/hacf-fr/sfrbox-api
